nonebot_plugin_queqiaoqiao/__init__.py
nonebot_plugin_queqiaoqiao/common.py
nonebot_plugin_queqiaoqiao/config.py
nonebot_plugin_queqiaoqiao/on_mc_msg.py
nonebot_plugin_queqiaoqiao-0.0.3.dist-info/LICENSE
nonebot_plugin_queqiaoqiao-0.0.3.dist-info/METADATA
nonebot_plugin_queqiaoqiao-0.0.3.dist-info/WHEEL
nonebot_plugin_queqiaoqiao-0.0.3.dist-info/RECORD
