Metadata-Version: 2.3
Name: nonebot-plugin-queqiaoqiao
Version: 0.0.3
Summary: 基于鹊桥的同步多个Minecraft服务器消息的插件
License: MIT
Author: 17TheWord
Author-email: 17theword@gmail.com
Requires-Python: >=3.10,<4.0
Classifier: License :: OSI Approved :: MIT License
Classifier: Programming Language :: Python :: 3
Classifier: Programming Language :: Python :: 3.10
Classifier: Programming Language :: Python :: 3.11
Classifier: Programming Language :: Python :: 3.12
Classifier: Programming Language :: Python :: 3.13
Requires-Dist: nonebot-adapter-minecraft (>=1.4.2,<2.0.0)
Requires-Dist: nonebot2[fastapi,websockets] (>=2.4.2,<3.0.0)
Requires-Dist: pydantic (>=1.10.0,<3.0.0,!=2.5.0,!=2.5.1)
